rid_lib/__init__.py
rid_lib/consts.py
rid_lib/core.py
rid_lib/utils.py
rid_lib/_vendor/org/__init__.py
rid_lib/_vendor/org/webpki/__init__.py
rid_lib/_vendor/org/webpki/json/Canonicalize.py
rid_lib/_vendor/org/webpki/json/LICENSE
rid_lib/_vendor/org/webpki/json/LICENSE.PSF
rid_lib/_vendor/org/webpki/json/NumberToJson.py
rid_lib/_vendor/org/webpki/json/__init__.py
rid_lib/ext/__init__.py
rid_lib/ext/bundle.py
rid_lib/ext/cache.py
rid_lib/ext/manifest.py
rid_lib/ext/utils.py
rid_lib/types/__init__.py
rid_lib/types/discord_channel.py
rid_lib/types/discord_guild.py
rid_lib/types/discord_message.py
rid_lib/types/discord_user.py
rid_lib/types/gdrive_export.py
rid_lib/types/gdrive_file.py
rid_lib/types/gdrive_file_authors.py
rid_lib/types/hackmd_note.py
rid_lib/types/http_s.py
rid_lib/types/koi_net_edge.py
rid_lib/types/koi_net_node.py
rid_lib/types/normalized_text.py
rid_lib/types/slack_channel.py
rid_lib/types/slack_message.py
rid_lib/types/slack_user.py
rid_lib/types/slack_workspace.py
rid_lib-3.2.12.dist-info/METADATA
rid_lib-3.2.12.dist-info/WHEEL
rid_lib-3.2.12.dist-info/licenses/LICENSE
rid_lib-3.2.12.dist-info/RECORD
