Metadata-Version: 2.4
Name: rid-lib
Version: 3.2.12
Summary: Implementation of Reference Identifiers (RIDs) protocol in Python
Project-URL: Homepage, https://github.com/BlockScience/rid-lib/
Author-email: Luke Miller <luke@block.science>
License: MIT License
License-File: LICENSE
Requires-Python: >=3.10
Requires-Dist: pydantic>=2.10
Provides-Extra: dev
Requires-Dist: build; extra == 'dev'
Requires-Dist: pytest-cov>=6.0; extra == 'dev'
Requires-Dist: pytest>=8.0; extra == 'dev'
Requires-Dist: twine>=6.0; extra == 'dev'
